zip/__init__.py
zip/finder.py
zipinfo-0.1.dist-info/LICENSE
zipinfo-0.1.dist-info/METADATA
zipinfo-0.1.dist-info/WHEEL
zipinfo-0.1.dist-info/top_level.txt
zipinfo-0.1.dist-info/RECORD
