Metadata-Version: 2.1
Name: zipinfo
Version: 0.1
Summary: A package to find metadata about zip files.
Home-page: https://github.com/r0uted/zipinfo
Author: r0uted
Author-email: midway-bins-0u@icloud.com
License: UNKNOWN
Platform: UNKNOWN
Classifier: Programming Language :: Python :: 3
Classifier: License :: OSI Approved :: MIT License
Classifier: Operating System :: OS Independent
Requires-Python: >=3.6
License-File: LICENSE
